numeroprimo/__init__.py
NUMERO_PRIMO-1.0.dist-info/LICENSE.txt
NUMERO_PRIMO-1.0.dist-info/METADATA
NUMERO_PRIMO-1.0.dist-info/WHEEL
NUMERO_PRIMO-1.0.dist-info/top_level.txt
NUMERO_PRIMO-1.0.dist-info/RECORD
