Metadata-Version: 2.1
Name: NUMERO-PRIMO
Version: 1.0
Summary: A tool to know the prime numbers in an interval.
Home-page: UNKNOWN
Author: Justo Mota Márquez
Author-email: justomotamarquez@gmail.com
License: GNU GPLv3
Keywords: pynumeroprimo mathematical operations primenumbers prime numbers numeros primos matematicas operaciones
Platform: UNKNOWN
Classifier: Development Status :: 4 - Beta
Classifier: Intended Audience :: Developers
Classifier: Topic :: Utilities
Classifier: License :: OSI Approved :: GNU General Public License v3 (GPLv3)
Classifier: Programming Language :: Python :: 3
Classifier: Operating System :: OS Independent
